<navigation:ExamplePage xmlns:navigation="navigation/example-page" loaded="onPageLoaded" xmlns:chart="nativescript-ui-chart" xmlns="http://www.nativescript.org/tns.xsd">
    <chart:RadCartesianChart id="cartesianChart">
        <chart:RadCartesianChart.horizontalAxis>
            <chart:DateTimeContinuousAxis
                minimum="01/02/2015" maximum="01/10/2015"
                majorStep="1" majorStepUnit="Month" dateFormat="MMM-dd"
                labelFitMode="Rotate" labelRotationAngle="1.2">
            </chart:DateTimeContinuousAxis>
        </chart:RadCartesianChart.horizontalAxis>
        <chart:RadCartesianChart.verticalAxis>
            <chart:LinearAxis/>
        </chart:RadCartesianChart.verticalAxis>

        <chart:RadCartesianChart.series>
            <chart:LineSeries items="{{ dateTimeSource }}" categoryProperty="timeStamp" valueProperty="Amount"/>
        </chart:RadCartesianChart.series>
    </chart:RadCartesianChart>
</navigation:ExamplePage>